zarrnii/__init__.py
zarrnii/_version.py
zarrnii/analysis.py
zarrnii/atlas.py
zarrnii/cli.py
zarrnii/core.py
zarrnii/enums.py
zarrnii/transform.py
zarrnii/plugins/__init__.py
zarrnii/plugins/hookspecs.py
zarrnii/plugins/plugin_manager.py
zarrnii/plugins/scaled_processing/__init__.py
zarrnii/plugins/scaled_processing/base.py
zarrnii/plugins/scaled_processing/gaussian_biasfield.py
zarrnii/plugins/scaled_processing/n4_biasfield.py
zarrnii/plugins/segmentation/__init__.py
zarrnii/plugins/segmentation/base.py
zarrnii/plugins/segmentation/local_otsu.py
zarrnii/plugins/segmentation/threshold.py
zarrnii-0.9.0a1.dist-info/METADATA
zarrnii-0.9.0a1.dist-info/WHEEL
zarrnii-0.9.0a1.dist-info/entry_points.txt
zarrnii-0.9.0a1.dist-info/RECORD
