Metadata-Version: 2.4
Name: zarrnii
Version: 0.9.0a1
Summary: Package for working with OME-Zarr and NIFTI images in a unified manner, with a focus on spatial transformations
Project-URL: Homepage, https://github.com/khanlab/zarrnii
Project-URL: Documentation, https://www.khanlab.ca/zarrnii
Project-URL: Repository, https://github.com/khanlab/zarrnii
Project-URL: Issues, https://github.com/khanlab/zarrnii/issues
Author-email: Ali Khan <alik@robarts.ca>
License: MIT
Keywords: biomedical,imaging,microscopy,mri,neuroimaging,nifti,ome-zarr
Classifier: Development Status :: 4 - Beta
Classifier: Intended Audience :: Science/Research
Classifier: License :: OSI Approved :: MIT License
Classifier: Operating System :: OS Independent
Classifier: Programming Language :: Python :: 3
Classifier: Programming Language :: Python :: 3.11
Classifier: Programming Language :: Python :: 3.12
Classifier: Topic :: Scientific/Engineering :: Image Processing
Classifier: Topic :: Scientific/Engineering :: Medical Science Apps.
Requires-Python: <3.14,>=3.11
Requires-Dist: dask>=2025.5.1
Requires-Dist: h5py>=3.14.0
Requires-Dist: ngff-zarr[all]>=0.13.1
Requires-Dist: nibabel>=5.2.0
Requires-Dist: numpy>=1.26.4
Requires-Dist: ome-zarr>=0.12.0
Requires-Dist: pandas>=2.2.0
Requires-Dist: pluggy>=1.0.0
Requires-Dist: pyyaml>=6.0
Requires-Dist: scikit-image>=0.22.0
Requires-Dist: scipy>=1.12.0
Requires-Dist: zarr>=3.0.8
Provides-Extra: dev
Requires-Dist: black>=24.10.0; extra == 'dev'
Requires-Dist: bokeh>=3.4.1; extra == 'dev'
Requires-Dist: flake8-bugbear>=24.12.12; extra == 'dev'
Requires-Dist: flake8-docstrings>=1.7.0; extra == 'dev'
Requires-Dist: flake8-import-order>=0.18.2; extra == 'dev'
Requires-Dist: flake8>=7.3.0; extra == 'dev'
Requires-Dist: isort>=5.13.2; extra == 'dev'
Requires-Dist: jupyterlab>=4.2.1; extra == 'dev'
Requires-Dist: matplotlib>=3.9.0; extra == 'dev'
Requires-Dist: mkdocs-material>=9.5.50; extra == 'dev'
Requires-Dist: mkdocs>=1.6.1; extra == 'dev'
Requires-Dist: mkdocstrings-python>=1.13.0; extra == 'dev'
Requires-Dist: mkdocstrings>=0.27.0; extra == 'dev'
Requires-Dist: pre-commit>=4.0.0; extra == 'dev'
Requires-Dist: pytest-cov>=6.0.0; extra == 'dev'
Requires-Dist: pytest>=8.2.0; extra == 'dev'
Provides-Extra: imaris
Requires-Dist: h5py>=3.8.0; extra == 'imaris'
Provides-Extra: n4
Requires-Dist: antspyx>=0.5.0; extra == 'n4'
Provides-Extra: templateflow
Requires-Dist: templateflow>=0.8.0; extra == 'templateflow'
